{
	"editor": {
		"allAngles": false,
		"entityTextureMode": false
	},
	"textureWidth": 16,
	"textureHeight": 16,
	"textureSizes": {
	},
	"textures": {
		"blueberry14": "C:/Users/gcamp/AppData/Roaming/Vintagestory/assets/survival/textures/block/plant/berrybush/ripe/blueberry1",
		"sticks1": "C:/Users/gcamp/AppData/Roaming/Vintagestory/assets/survival/textures/block/plant/fruittree/sticks1",
		"blueberry1": "C:/Users/gcamp/AppData/Roaming/Vintagestory/assets/survival/textures/block/plant/berrybush/leaves/blueberry1"
	},
	"elements": [
		{
			"name": "origin",
			"from": [ 8.0, 0.0, 8.0 ], 
			"to": [ 8.0, 0.0, 8.0 ], 
			"rotationOrigin": [ 8.0, 0.0, 8.0 ],
			"faces": {
				"north": { "texture": "#null", "uv": [ 11.0, 4.0, 11.5, 4.5 ], "enabled": false },
				"east": { "texture": "#null", "uv": [ 13.5, 1.5, 14.0, 2.0 ], "enabled": false },
				"south": { "texture": "#null", "uv": [ 8.5, 11.5, 9.0, 12.0 ], "enabled": false },
				"west": { "texture": "#null", "uv": [ 7.5, 6.5, 8.0, 7.0 ], "enabled": false },
				"up": { "texture": "#null", "uv": [ 14.0, 3.5, 14.5, 4.0 ], "enabled": false },
				"down": { "texture": "#null", "uv": [ 4.5, 8.5, 5.0, 9.0 ], "enabled": false }
			},
			"children": [
				{
					"name": "Leaves",
					"from": [ -6.0, 3.0, -6.0 ], 
					"to": [ 6.0, 15.0, 6.0 ], 
					"climateColorMap": "climatePlantTint",
					"seasonColorMap": "seasonalFoliage",
					"rotationOrigin": [ -6.0, 3.0, -6.0 ],
					"faces": {
						"north": { "texture": "#blueberry1", "uv": [ 1.0, 1.0, 15.0, 15.0 ], "autoUv": false, "windMode": [-1,1,1,-1] },
						"east": { "texture": "#blueberry1", "uv": [ 1.0, 1.0, 15.0, 15.0 ], "autoUv": false, "windMode": [-1,1,1,-1] },
						"south": { "texture": "#blueberry1", "uv": [ 1.0, 1.0, 15.0, 15.0 ], "autoUv": false, "windMode": [-1,-1,1,1] },
						"west": { "texture": "#blueberry1", "uv": [ 1.0, 1.0, 15.0, 15.0 ], "autoUv": false, "windMode": [-1,-1,1,1] },
						"up": { "texture": "#blueberry1", "uv": [ 1.0, 1.0, 15.0, 15.0 ], "autoUv": false, "windMode": [1,1,1,1] },
						"down": { "texture": "#blueberry1", "uv": [ 0.0, 0.0, 15.0, 15.0 ], "enabled": false, "autoUv": false }
					}
				},
				{
					"name": "Branches",
					"from": [ -6.0, 0.0, 0.0 ], 
					"to": [ 6.0, 12.0, 0.0 ], 
					"climateColorMap": "climatePlantTint",
					"seasonColorMap": "seasonalFoliage",
					"rotationOrigin": [ -1.0, 0.0, 0.0 ],
					"faces": {
						"north": { "texture": "#sticks1", "uv": [ 0.0, 0.0, 16.0, 16.0 ], "autoUv": false, "windMode": [1,1,1,1] },
						"east": { "texture": "#sticks1", "uv": [ 0.0, 0.0, 0.5, 12.0 ], "enabled": false },
						"south": { "texture": "#sticks1", "uv": [ 0.0, 0.0, 12.0, 12.0 ], "enabled": false },
						"west": { "texture": "#sticks1", "uv": [ 0.0, 0.0, 0.5, 12.0 ], "enabled": false },
						"up": { "texture": "#sticks1", "uv": [ 0.0, 0.0, 12.0, 0.5 ], "enabled": false },
						"down": { "texture": "#sticks1", "uv": [ 0.0, 0.0, 12.0, 0.5 ], "enabled": false, "windMode": [1,1,1,1] }
					}
				},
				{
					"name": "Branches2",
					"from": [ -5.0, 0.0, -1.0 ], 
					"to": [ 7.0, 12.0, -1.0 ], 
					"climateColorMap": "climatePlantTint",
					"seasonColorMap": "seasonalFoliage",
					"rotationOrigin": [ 0.0, 0.0, -1.0 ],
					"rotationY": -90.0,
					"faces": {
						"north": { "texture": "#sticks1", "uv": [ 0.0, 0.0, 16.0, 16.0 ], "autoUv": false, "windMode": [1,1,1,1] },
						"east": { "texture": "#leaves", "uv": [ 0.0, 0.0, 0.5, 12.0 ], "enabled": false },
						"south": { "texture": "#leaves", "uv": [ 0.0, 0.0, 12.0, 12.0 ], "enabled": false },
						"west": { "texture": "#leaves", "uv": [ 0.0, 0.0, 0.5, 12.0 ], "enabled": false },
						"up": { "texture": "#leaves", "uv": [ 0.0, 0.0, 12.0, 0.5 ], "enabled": false },
						"down": { "texture": "#leaves", "uv": [ 0.0, 0.0, 12.0, 0.5 ], "enabled": false }
					}
				},
				{
					"name": "Leaves2",
					"from": [ -8.0, 3.0, 3.0 ], 
					"to": [ 8.0, 19.0, 3.0 ], 
					"climateColorMap": "climatePlantTint",
					"seasonColorMap": "climatePlantTint",
					"rotationOrigin": [ 0.0, 3.0, 3.0 ],
					"rotationY": -22.5,
					"faces": {
						"north": { "texture": "#blueberry1", "uv": [ 0.5, 0.5, 15.5, 15.5 ], "autoUv": false },
						"east": { "texture": "#sticks1", "uv": [ 0.0, 0.0, 0.5, 16.0 ], "enabled": false },
						"south": { "texture": "#sticks1", "uv": [ 0.0, 0.0, 16.0, 16.0 ], "enabled": false },
						"west": { "texture": "#sticks1", "uv": [ 0.0, 0.0, 0.5, 16.0 ], "enabled": false },
						"up": { "texture": "#sticks1", "uv": [ 0.0, 0.0, 16.0, 0.5 ], "enabled": false },
						"down": { "texture": "#sticks1", "uv": [ 0.0, 0.0, 16.0, 0.5 ], "enabled": false }
					}
				},
				{
					"name": "Leaves6",
					"from": [ -9.0, 3.0, -4.0 ], 
					"to": [ 7.0, 19.0, -4.0 ], 
					"climateColorMap": "climatePlantTint",
					"seasonColorMap": "climatePlantTint",
					"rotationOrigin": [ 0.0, 3.0, -1.0 ],
					"rotationY": 45.0,
					"faces": {
						"north": { "texture": "#blueberry1", "uv": [ 0.5, 0.5, 15.5, 15.5 ], "autoUv": false },
						"east": { "texture": "#sticks1", "uv": [ 0.0, 0.0, 0.5, 16.0 ], "enabled": false },
						"south": { "texture": "#sticks1", "uv": [ 0.0, 0.0, 16.0, 16.0 ], "enabled": false },
						"west": { "texture": "#sticks1", "uv": [ 0.0, 0.0, 0.5, 16.0 ], "enabled": false },
						"up": { "texture": "#sticks1", "uv": [ 0.0, 0.0, 16.0, 0.5 ], "enabled": false },
						"down": { "texture": "#sticks1", "uv": [ 0.0, 0.0, 16.0, 0.5 ], "enabled": false }
					}
				},
				{
					"name": "Leaves7",
					"from": [ -5.0, 3.0, 0.0 ], 
					"to": [ 11.0, 19.0, 0.0 ], 
					"climateColorMap": "climatePlantTint",
					"seasonColorMap": "climatePlantTint",
					"rotationOrigin": [ 3.0, 3.0, 0.0 ],
					"rotationY": 90.0,
					"faces": {
						"north": { "texture": "#blueberry1", "uv": [ 0.5, 0.5, 15.5, 15.5 ], "autoUv": false },
						"east": { "texture": "#sticks1", "uv": [ 0.0, 0.0, 0.5, 16.0 ], "enabled": false },
						"south": { "texture": "#sticks1", "uv": [ 0.0, 0.0, 16.0, 16.0 ], "enabled": false },
						"west": { "texture": "#sticks1", "uv": [ 0.0, 0.0, 0.5, 16.0 ], "enabled": false },
						"up": { "texture": "#sticks1", "uv": [ 0.0, 0.0, 16.0, 0.5 ], "enabled": false },
						"down": { "texture": "#sticks1", "uv": [ 0.0, 0.0, 16.0, 0.5 ], "enabled": false }
					}
				},
				{
					"name": "Flowers",
					"from": [ -6.1, 2.9, -6.1 ], 
					"to": [ 6.1, 15.1, 6.1 ], 
					"climateColorMap": "climatePlantTint",
					"seasonColorMap": "climatePlantTint",
					"rotationOrigin": [ -6.1, 2.9, -6.1 ],
					"faces": {
						"north": { "texture": "#blueberry14", "uv": [ 0.0, 0.0, 15.0, 15.0 ], "autoUv": false, "windMode": [-1,-1,-1,-1] },
						"east": { "texture": "#blueberry14", "uv": [ 0.0, 0.0, 15.0, 15.0 ], "autoUv": false },
						"south": { "texture": "#blueberry14", "uv": [ 0.0, 0.0, 15.0, 15.0 ], "autoUv": false },
						"west": { "texture": "#blueberry14", "uv": [ 0.0, 0.0, 15.0, 15.0 ], "autoUv": false },
						"up": { "texture": "#blueberry14", "uv": [ 0.0, 0.0, 15.0, 15.0 ], "autoUv": false },
						"down": { "texture": "#blueberry14", "uv": [ 1.0, 1.0, 15.0, 15.0 ], "enabled": false, "autoUv": false }
					}
				},
				{
					"name": "Flowers2",
					"from": [ -8.1, 2.9, 2.9 ], 
					"to": [ 8.1, 19.1, 3.1 ], 
					"climateColorMap": "climatePlantTint",
					"seasonColorMap": "climatePlantTint",
					"rotationOrigin": [ -0.1, 2.9, 2.9 ],
					"rotationY": -22.5,
					"faces": {
						"north": { "texture": "#blueberry14", "uv": [ 0.0, 0.0, 15.0, 15.0 ], "autoUv": false },
						"east": { "texture": "#blueberry14", "uv": [ 0.0, 0.0, 0.5, 16.0 ], "enabled": false },
						"south": { "texture": "#blueberry14", "uv": [ 0.0, 0.0, 15.0, 15.0 ], "autoUv": false, "windMode": [-1,-1,-1,-1], "windData": [0,0,1,1] },
						"west": { "texture": "#blueberry14", "uv": [ 0.0, 0.0, 0.5, 16.0 ], "enabled": false },
						"up": { "texture": "#blueberry14", "uv": [ 0.0, 0.0, 16.0, 0.5 ], "enabled": false },
						"down": { "texture": "#blueberry14", "uv": [ 0.0, 0.0, 16.0, 0.5 ], "enabled": false }
					}
				},
				{
					"name": "Flowers3",
					"from": [ -9.1, 2.9, -4.1 ], 
					"to": [ 7.1, 19.1, -3.9 ], 
					"climateColorMap": "climatePlantTint",
					"seasonColorMap": "climatePlantTint",
					"rotationOrigin": [ -0.1, 2.9, -1.1 ],
					"rotationY": 45.0,
					"faces": {
						"north": { "texture": "#blueberry14", "uv": [ 0.0, 0.0, 15.0, 15.0 ], "autoUv": false },
						"east": { "texture": "#blueberry14", "uv": [ 0.0, 0.0, 0.5, 16.0 ], "enabled": false },
						"south": { "texture": "#blueberry14", "uv": [ 0.0, 0.0, 15.0, 15.0 ], "autoUv": false, "windMode": [-1,-1,-1,-1], "windData": [0,0,1,1] },
						"west": { "texture": "#blueberry14", "uv": [ 0.0, 0.0, 0.5, 16.0 ], "enabled": false },
						"up": { "texture": "#blueberry14", "uv": [ 0.0, 0.0, 16.0, 0.5 ], "enabled": false },
						"down": { "texture": "#blueberry14", "uv": [ 0.0, 0.0, 16.0, 0.5 ], "enabled": false }
					}
				},
				{
					"name": "Flowers4",
					"from": [ -5.1, 2.9, -0.1 ], 
					"to": [ 11.1, 19.1, 0.1 ], 
					"climateColorMap": "climatePlantTint",
					"seasonColorMap": "climatePlantTint",
					"rotationOrigin": [ 2.9, 2.9, -0.1 ],
					"rotationY": 90.0,
					"faces": {
						"north": { "texture": "#blueberry14", "uv": [ 0.0, 0.0, 15.0, 15.0 ], "autoUv": false },
						"east": { "texture": "#blueberry14", "uv": [ 0.0, 0.0, 0.5, 16.0 ], "enabled": false },
						"south": { "texture": "#blueberry14", "uv": [ 0.0, 0.0, 15.0, 15.0 ], "autoUv": false, "windMode": [-1,-1,-1,-1], "windData": [0,0,1,1] },
						"west": { "texture": "#blueberry14", "uv": [ 0.0, 0.0, 0.5, 16.0 ], "enabled": false },
						"up": { "texture": "#blueberry14", "uv": [ 0.0, 0.0, 16.0, 0.5 ], "enabled": false },
						"down": { "texture": "#blueberry14", "uv": [ 0.0, 0.0, 16.0, 0.5 ], "enabled": false }
					}
				}
			]
		}
	]}