[
    {
        "ingredientPattern": "\"SL\tSP\tSM\"",
        "requiresTrait": "Engineer",
        "ingredients": {
            "L": {
                "type": "item",
                "code": "game:leather-plain",
                "quantity": 1
            },
            "M": {
                "type": "item",
                "code": "game:leather-plain",
                "quantity": 1
            },
            "P": {
                "type": "item",
                "code": "game:paper-parchment",
                "quantity": 16
            },
            "S": {
                "type": "item",
                "code": "medieval:stripsofleather",
                "quantity": 2
            }
        },
        "width": 2,
        "height": 3,
        "name": "backpack",
        "output": {
            "type": "item",
            "code": "game:book-normal-brickred"
        }
    },
    {
        "ingredientPattern": "\"SL\tSP\tSM\"",
        "requiresTrait": "Engineer",
        "ingredients": {
            "L": {
                "type": "item",
                "code": "game:leather-red",
                "quantity": 1
            },
            "M": {
                "type": "item",
                "code": "game:leather-red",
                "quantity": 1
            },
            "P": {
                "type": "item",
                "code": "game:paper-parchment",
                "quantity": 16
            },
            "S": {
                "type": "item",
                "code": "medieval:stripsofleather",
                "quantity": 2
            }
        },
        "width": 2,
        "height": 3,
        "name": "backpack",
        "output": {
            "type": "item",
            "code": "game:book-normal-cherryred"
        }
    },
    {
        "ingredientPattern": "\"SL\tSP\tSM\"",
        "requiresTrait": "Engineer",
        "ingredients": {
            "L": {
                "type": "item",
                "code": "game:leather-yellow",
                "quantity": 1
            },
            "M": {
                "type": "item",
                "code": "game:leather-plain",
                "quantity": 1
            },
            "P": {
                "type": "item",
                "code": "game:paper-parchment",
                "quantity": 16
            },
            "S": {
                "type": "item",
                "code": "medieval:stripsofleather",
                "quantity": 2
            }
        },
        "width": 2,
        "height": 3,
        "name": "backpack",
        "output": {
            "type": "item",
            "code": "game:book-normal-darkbeige"
        }
    },
    {
        "ingredientPattern": "\"SL\tSP\tSM\"",
        "requiresTrait": "Engineer",
        "ingredients": {
            "L": {
                "type": "item",
                "code": "game:leather-gray",
                "quantity": 1
            },
            "M": {
                "type": "item",
                "code": "game:leather-black",
                "quantity": 1
            },
            "P": {
                "type": "item",
                "code": "game:paper-parchment",
                "quantity": 16
            },
            "S": {
                "type": "item",
                "code": "medieval:stripsofleather",
                "quantity": 2
            }
        },
        "width": 2,
        "height": 3,
        "name": "backpack",
        "output": {
            "type": "item",
            "code": "game:book-normal-darkgray"
        }
    },
    {
        "ingredientPattern": "\"SL\tSP\tSM\"",
        "requiresTrait": "Engineer",
        "ingredients": {
            "L": {
                "type": "item",
                "code": "game:leather-green",
                "quantity": 1
            },
            "M": {
                "type": "item",
                "code": "game:leather-black",
                "quantity": 1
            },
            "P": {
                "type": "item",
                "code": "game:paper-parchment",
                "quantity": 16
            },
            "S": {
                "type": "item",
                "code": "medieval:stripsofleather",
                "quantity": 2
            }
        },
        "width": 2,
        "height": 3,
        "name": "backpack",
        "output": {
            "type": "item",
            "code": "game:book-normal-darkgreen"
        }
    },
    {
        "ingredientPattern": "\"SL\tSP\tSM\"",
        "requiresTrait": "Engineer",
        "ingredients": {
            "L": {
                "type": "item",
                "code": "game:leather-green",
                "quantity": 1
            },
            "M": {
                "type": "item",
                "code": "game:leather-gray",
                "quantity": 1
            },
            "P": {
                "type": "item",
                "code": "game:paper-parchment",
                "quantity": 16
            },
            "S": {
                "type": "item",
                "code": "medieval:stripsofleather",
                "quantity": 2
            }
        },
        "width": 2,
        "height": 3,
        "name": "backpack",
        "output": {
            "type": "item",
            "code": "game:book-normal-darkolive"
        }
    },
    {
        "ingredientPattern": "\"SL\tSP\tSM\"",
        "requiresTrait": "Engineer",
        "ingredients": {
            "L": {
                "type": "item",
                "code": "game:leather-gray",
                "quantity": 1
            },
            "M": {
                "type": "item",
                "code": "game:leather-gray",
                "quantity": 1
            },
            "P": {
                "type": "item",
                "code": "game:paper-parchment",
                "quantity": 16
            },
            "S": {
                "type": "item",
                "code": "medieval:stripsofleather",
                "quantity": 2
            }
        },
        "width": 2,
        "height": 3,
        "name": "backpack",
        "output": {
            "type": "item",
            "code": "game:book-normal-gray"
        }
    },
    {
        "ingredientPattern": "\"SL\tSP\tSM\"",
        "requiresTrait": "Engineer",
        "ingredients": {
            "L": {
                "type": "item",
                "code": "game:leather-yellow",
                "quantity": 1
            },
            "M": {
                "type": "item",
                "code": "game:leather-green",
                "quantity": 1
            },
            "P": {
                "type": "item",
                "code": "game:paper-parchment",
                "quantity": 16
            },
            "S": {
                "type": "item",
                "code": "medieval:stripsofleather",
                "quantity": 2
            }
        },
        "width": 2,
        "height": 3,
        "name": "backpack",
        "output": {
            "type": "item",
            "code": "game:book-normal-olive"
        }
    },
    {
        "ingredientPattern": "\"SL\tSP\tSM\"",
        "ingredients": {
            "L": {
                "type": "item",
                "code": "game:leather-orange",
                "quantity": 1
            },
            "M": {
                "type": "item",
                "code": "game:leather-orange",
                "quantity": 1
            },
            "P": {
                "type": "item",
                "code": "game:paper-parchment",
                "quantity": 16
            },
            "S": {
                "type": "item",
                "code": "medieval:stripsofleather",
                "quantity": 2
            }
        },
        "width": 2,
        "height": 3,
        "name": "backpack",
        "output": {
            "type": "item",
            "code": "game:book-normal-orange"
        }
    },
    {
        "ingredientPattern": "\"SL\tSP\tSM\"",
        "requiresTrait": "Engineer",
        "ingredients": {
            "L": {
                "type": "item",
                "code": "game:leather-orange",
                "quantity": 1
            },
            "M": {
                "type": "item",
                "code": "game:leather-plain",
                "quantity": 1
            },
            "P": {
                "type": "item",
                "code": "game:paper-parchment",
                "quantity": 16
            },
            "S": {
                "type": "item",
                "code": "medieval:stripsofleather",
                "quantity": 2
            }
        },
        "width": 2,
        "height": 3,
        "name": "backpack",
        "output": {
            "type": "item",
            "code": "game:book-normal-orangebrown"
        }
    },
    {
        "ingredientPattern": "\"SL\tSP\tSM\"",
        "requiresTrait": "Engineer",
        "ingredients": {
            "L": {
                "type": "item",
                "code": "game:leather-purple",
                "quantity": 1
            },
            "M": {
                "type": "item",
                "code": "game:leather-purple",
                "quantity": 1
            },
            "P": {
                "type": "item",
                "code": "game:paper-parchment",
                "quantity": 16
            },
            "S": {
                "type": "item",
                "code": "medieval:stripsofleather",
                "quantity": 2
            }
        },
        "width": 2,
        "height": 3,
        "name": "backpack",
        "output": {
            "type": "item",
            "code": "game:book-normal-purple"
        }
    },
    {
        "ingredientPattern": "\"SL\tSP\tSM\"",
        "requiresTrait": "Engineer",
        "ingredients": {
            "L": {
                "type": "item",
                "code": "game:leather-orange",
                "quantity": 1
            },
            "M": {
                "type": "item",
                "code": "game:leather-purple",
                "quantity": 1
            },
            "P": {
                "type": "item",
                "code": "game:paper-parchment",
                "quantity": 16
            },
            "S": {
                "type": "item",
                "code": "medieval:stripsofleather",
                "quantity": 2
            }
        },
        "width": 2,
        "height": 3,
        "name": "backpack",
        "output": {
            "type": "item",
            "code": "game:book-normal-purpleorange"
        }
    },
    {
        "ingredientPattern": "\"SL\tSP\tSM\"",
        "requiresTrait": "Engineer",
        "ingredients": {
            "L": {
                "type": "item",
                "code": "game:leather-blue",
                "quantity": 1
            },
            "M": {
                "type": "item",
                "code": "game:leather-green",
                "quantity": 1
            },
            "P": {
                "type": "item",
                "code": "game:paper-parchment",
                "quantity": 16
            },
            "S": {
                "type": "item",
                "code": "medieval:stripsofleather",
                "quantity": 2
            }
        },
        "width": 2,
        "height": 3,
        "name": "backpack",
        "output": {
            "type": "item",
            "code": "game:book-normal-teal"
        }
    }
]